{"CAAScdMaiUseCases": {"FileList":["CAAMaiToolListDocumentation.htm","CAAMaiInsertPPInstruction.htm","CAAMaiMachiningPatternCreationSource.htm","CAAMaiToolListSource.htm","CAAMaiInsertPPInstructionSource.htm","Assembly1.html","Assembly3.html","Assembly2.html","CAAMaiManageMachiningAxisSystemSource.htm","CAAMaiManageMachiningAxisSystem.htm","CAAMaiInsertLatheToolMotionSource.htm","CAAMaiInsertAxialToolMotionSource.htm","CAAMaiInsertAxialToolMotion.htm","CAAMaiInsertLatheToolMotion.htm","ToolList.html","CAAMaiInitializeSetUp.htm","CAAMaiMachiningPatternCreation.htm","CAAMaiInitializeSetUpSource.htm"],"TitleList":["Generating an HTML Documentation from a Tool List","Inserting a PP Instruction before a Specified Activity","CAAMaiMachiningPatternCreationSource.CATScript","toollist.CATScript","CAAMaiInsertPPInstruction.CATScript","Assembly 1 : Assembly_3","Assembly 3 : Assembly_4","Assembly 2 : Assembly_2","CAAMaiManageMachiningAxisSystem.CATScript","Managing a Machining Axis System Activity","Language","CAAMaiInsertAxialToolMotion.CATScript","Inserting Axial Tool Motion in a Point To Point Activity","Inserting Lathe Tool Motions in a Sequential Activity","Tools List Documentation","Loading the Machining Workbench and Initializing the Setup Activity","Creating a Machining Pattern","CAAMaiInitializeSetUp.CATScript"],"WordList":{"afilesyst":[9],"deactivates":[65536],"thelogstream.close":[8],"references":[111107],"currentsetup":[9],"thefolders":[8],"copie":[8],"objects":[111107],"process1.catprocess":[16384],"defname":[18],"endofgenerationtxt":[8],"your":[8],"nlintthd":[8],"childs":[245534],"tmlist2":[6144],"without":[8192],"mfginternaltool":[8],"setting":[4],"these":[77828],"change.1":[16384],"change.2":[16384],"opendocnow":[8],"change.3":[16384],"change.4":[16384],"absent":[8],"toollist.catprocess":[8],"mfgpatternusage":[65540],"sample_part.catpart":[770],"utilise":[8],"subdir.count":[8],"assigning":[4],"afolder.files":[8],"anobj":[8],"imagecorr":[8],"delfolder":[8],"firstrelimitingelement":[15360],"stdcomponentsdir":[8],"ecriture":[8],"contains":[12288],"folder":[8],"selection":[4],"size":[8],"reserved":[111107],"nccenter":[8],"d'environnement":[8],"htmlfilesroot":[8],"bidvar":[8],"manpattern":[65540],"processactivities.count":[8],"machine1":[9216],"object":[4096],"valuatefromstring":[65540],"lire":[8],"drilling.1":[16384],"toolmotion":[7168],"mfgsquareinsert":[8],"offsetvalue.value":[6144],"currentactivity":[9],"caamaimanagemachiningaxissystem":[514],"result":[8],"same":[8192],"attribut.value":[9],"tabassemblyname":[8],"currentsetup.programs":[9],"mfgdiamondinsert":[8],"anenvvar":[8],"reversing":[4],"catia.filesystem":[9],"d'une":[8],"tooldiameter":[8],"linked":[78340],"hybridbody1.hybridshapes":[16128],"resume":[8],"a":[243231],"addparametertoarray":[8],"b":[8],"createonetoolsheet":[8],"d":[6144],"sets":[111106],"i":[245535],"j":[9],"k":[9],"mfgview":[66308],"l":[8],"3333ff":[8],"diameterid":[8],"mfgboringbartool":[8],"p":[8],"the":[245279],"numberofpo":[179986],"repcont":[8],"valuated":[8192],"fifth":[8192],"information":[1],"inserts":[12288],"thelogfile":[8],"standard":[8192],"teste":[8],"couple":[65536],"notes":[8],"aparametername":[8],"correct":[18],"nlintgrv":[8],"ncconmil":[8],"currentassembly.assemblytype":[8],"tonls":[8],"deactivate":[65536],"cmdline":[8],"generated":[1],"currenttool.number":[9],"rel":[768],"mfgapttool":[8],"assigns":[78336],"line3":[7168],"rectpattern.1":[65540],"rep":[8],"eightth":[8192],"line2":[7168],"assemblycomment":[8],"line1":[7168],"add":[65567],"par":[8],"pas":[8],"asstool.getattribute":[8],"actcur.name":[18],"its":[12802],"anyobject":[200478],"check":[14336],"chr":[8],"list":[30729],"external":[9216],"boite":[8],"caamaiinitializesetup":[32768],"anactivity":[8],"thetype":[8],"useful":[12288],"child":[245526],"deldir":[8],"closelogfile":[8],"directory":[8],"remove":[65540],"filecount":[8],"root":[212484],"createhtmlfilesroot":[8],"tm2":[15360],"tm1":[15360],"anassembly.tool":[8],"end":[245535],"tm4":[9216],"atool.getattribute":[8],"catia.documents.open":[8],"tm3":[15360],"tm6":[9216],"currentactivity.name":[9],"tm5":[9216],"tm8":[9216],"actname":[18],"tm7":[9216],"fso.folderexists":[8],"erreur":[8],"pour":[8],"activites":[8],"mfgactivities":[3080],"toollist.catscript":[1],"filesystem":[9],"modify":[65540],"with":[40963],"fso.getfolder":[8],"referenced":[18],"moves":[2],"existlogods":[8],"partmachined":[15360],"pdu":[8],"copyright":[111107],"mfglatheeodeltacheckmode":[9216],"eol":[8],"aninsert.inserttype":[8],"writetooltable":[8],"caamaiinsertlathetoolmotion.catscript":[8192],"strlength":[8],"toolcomment":[8],"number":[78348],"writeassembly":[8],"assemblytype":[8],"mfgdoc1":[81695],"physicalactivity":[245534],"defaulthtmlfilename":[8],"nlgroove":[8],"property":[8192],"procede":[8],"milling":[8],"thefiles":[8],"order":[1],"usedtoolnb":[8],"afilesystem":[8],"textes":[8],"shape":[65540],"bidstr":[8],"programmes":[8],"nothing":[8],"programmer":[78342],"specify":[2],"script":[3092],"thefolders.count":[8],"exit":[245534],"system":[520],"drives":[6144],"seventh":[8192],"nctaps":[8],"theassemblyfile":[8],"afilesyst.createfile":[9],"manpattern.removepartsurfaces":[4],"indirv":[9216],"foldername":[8],"mfggrooveinsert":[8],"manufacturingfeatures":[66308],"partdoc1.name":[768],"progactivitylist.count":[8],"caamaimachiningpatterncreation":[65536],"parametre":[8],"goto":[8],"top":[111111],"mfgmachiningaxissystem":[768],"manpattern.addposition":[65540],"rights":[111107],"have":[8193],"activating":[4],"iexplore.exe":[8],"initialise":[8],"thepprdoc.getitem":[131072],"product":[245508],"50mm":[65540],"acorr.diameter":[8],"mfgcenterdrilltool":[8],"programlist":[16155],"nlextgrv":[8],"insertname":[8],"mfgcheckstopmode":[6144],"cession":[8],"nbfolders":[8],"pocketing.1":[16384],"names":[12288],"currenttool":[9],"stored":[8192],"deactivating":[4],"removes":[65536],"atool.picture":[8],"envvar":[8],"est":[8],"modifies":[4096],"acorr.point":[8],"body":[80900],"outindex":[9],"apath":[8],"nctschmf":[8],"associate":[131072],"points":[8196],"mode":[77828],"mfggroovefrontaltool":[8],"automation":[111107],"mfglatheeovaluedistance":[9216],"aninsert":[8],"function":[8],"pointsite":[6144],"all":[111107],"aninsert.getattribute":[8],"border":[8],"new":[163840],"numbering":[65540],"including":[3072],"read":[65549],"aprocess.issubtypeof":[8],"activitylist.getelement":[9],"program1.appendoperation":[16128],"manpattern.startpoint":[65540],"tool":[31753],"outils":[8],"usedtool":[8],"atool.name":[8],"activate":[65536],"tooltype":[8],"filespath":[8],"mfgdeltaparallelline":[4096],"catia.systemservice.executebackgroundprocessus":[8],"motion's":[15360],"fichiers":[8],"mfg_cone_length":[8],"anassembly.number":[8],"atool.comment":[8],"point1":[7168],"point2":[7168],"ncbochmf":[8],"point3":[7168],"currentactivity.tool":[9],"updatelogfile":[8],"currentassembly.number":[9],"and":[245279],"design":[200196],"define":[8200],"checkmode.valuatefromstring":[6144],"defini":[8],"htmldefaultdocdir":[8],"direction":[512],"mfgprojectpattern":[65540],"corrpoint":[8],"mfgtslottertool":[8],"mfgseqmotionppword":[9216],"mfgreamertool":[8],"cmderreur":[8],"mfgtoppattern":[4],"opening":[8],"reverses":[65536],"declarations":[768],"catpart":[208896],"manufacturingview":[66308],"acmdresult":[8],"mfg_name":[9],"possibilite":[8],"associe":[8],"application":[163840],"catstartuppath":[8],"activities":[101901],"getinsertimage":[8],"crlf":[8],"acorr":[8],"mfggrooveexternaltool":[8],"defines":[8192],"progactivitylist":[8],"ncconmilcomp.gif":[8],"textstream":[9],"atool.getcorrector":[8],"len":[8],"setgeometry":[12288],"manpattern.activatepoint":[65540],"modele":[8],"corrdiameter":[8],"les":[8],"repertoire":[8],"afilesystem.folderexists":[8],"mfgseqmotionlathedelta":[9216],"defined":[65560],"element":[12288],"program1.addppinstruction":[18],"documents1.item":[80900],"using":[12288],"mfggrooveinternaltool":[8],"tm1.setgeometry":[15360],"containing":[65536],"want":[16],"nbcorr":[8],"completed":[1],"each":[6144],"msgbox":[12040],"specifying":[8192],"creating":[98316],"mfgtool-list":[8],"createsystemvariables":[8],"vide":[8],"ncmddrlscomp.gif":[8],"scanning":[1],"document":[233247],"prevpos":[8],"document1":[8],"two":[8192],"manufacturinginsert":[8],"mfglathedeltaptpt":[9216],"theprocess.issubtypeof":[163840],"default":[8],"are":[8192],"attribute":[12288],"aline":[8],"commentaire":[8],"fso.deletefile":[8],"creation":[15368],"manpattern.addpartsurface":[65540],"modifying":[4100],"tm3.setgeometry":[15360],"anattribut.valueasstring":[8],"setupname":[8],"tm4.setgeometry":[9216],"envvalue":[8],"tm6.setgeometry":[9216],"ncapt":[8],"mfg_comment":[8],"tous":[8],"call":[16128],"p.o":[8],"mfgtoolmotions":[15360],"such":[1],"-1.0":[768],"parametres":[8],"catia.activedocument":[245535],"deltamode":[9216],"nls":[8],"nltrigon":[8],"relations":[768],"mfgthreadinsert":[8],"htmlfilesname":[8],"setup1.createmachine":[9216],"imgname":[8],"afilesyst.fileexists":[8],"documents":[68612],"run":[111110],"nlthread":[8],"source":[8],"myfeature.setoriginxdirection":[768],"cible":[8],"features":[66052],"view":[66052],"myfeature.name":[768],"atype":[8],"l'outil":[8],"activityref.childrenactivities":[81686],"has":[111107],"err.raise":[8],"starts":[163840],"manufacturingactivity":[26],"writeinserttable":[8],"att":[8],"activityline":[8],"last":[77824],"theprocess":[131072],"ceux":[8],"pt1":[9216],"astream.close":[8],"pt3":[9216],"pt2":[9216],"involved":[8],"nbfiles":[8],"machining":[244247],"partdoc1":[768],"name":[26],"thefolders.item":[8],"page":[8],"next":[245535],"facing.1":[16384],"thesetup":[163840],"color":[8],"distance":[73732],"string":[26],"aux":[8],"description":[12],"generating":[1],"non":[8],"catia":[111107],"processactivities.item":[8],"operation.1":[16384],"not":[8],"actinprog":[18],"systemes":[4],"now":[8],"designhole3":[65540],"mfgview.manufacturingfeatures.add":[768],"designhole2":[65540],"t-slotting.1":[16384],"dependantes":[8],"designhole4":[65540],"axissystems":[768],"designhole1":[65540],"filecopy":[8],"nlextthd":[8],"catia.systemservice.print":[8],"d'assemblies":[8],"atextstream.write":[8],"center":[8],"start":[65540],"hybridshapes1":[16128],"manage":[512],"target":[8],"partdocument1.part":[80900],"nlsresult":[8],"mfgpast":[4096],"aresource":[8],"short":[111107],"issemicolon":[8],"toolchangelathe":[9],"container":[8192],"redim":[8],"programlist.getelement":[16155],"program":[32539],"ajout":[8],"etre":[8],"when":[8192],"put":[65544],"toollist.log":[8],"shapes1":[65540],"modale":[8],"documents1":[80900],"nineth":[8192],"test2.name":[2048],"suppression":[8],"aprocess.childrenactivities":[8],"enter":[16],"atool.correctorcount":[8],"case":[111115],"tabassembly":[8],"catiatextstrean":[8],"generation":[16392],"images":[8],"item":[1],"nlround":[8],"valeur_du_parametre":[8],"currenttool.name":[9],"mfgmillanddrilltoolassembly":[16384],"thelogstream":[8],"tool-assembly":[8],"mfgspotdrilltool":[8],"usedinsert":[8],"myfeature.origin":[768],"posdernierslash":[8],"aninsert.comment":[8],"assembly_3":[16384],"quot":[13330],"assembly_4":[16384],"assembly_1":[16384],"assembly_2":[16384],"initialisation":[8],"actcur":[18],"log":[8],"adlodttmp":[8],"pattern":[66052],"programname":[8],"caamaiinsertppinstruction.catscript":[2],"c5c5e2":[8],"thetoolfile":[8],"toollist":[8],"colonnes":[8],"enables":[12288],"traites":[8],"t1_end_mill_d_10":[16384],"editor":[8],"means":[8192],"retourne":[8],"manufacturingprogram":[3858],"ncfacmil":[8],"prod":[66052],"thepprdoc.application":[163840],"more":[1],"htmlfilespath":[9],"ncbochmfcomp.gif":[8],"reverse":[65540],"defaulthtmleditor":[8],"recherche":[8],"ncdrillscomp.gif":[8],"test2":[6144],"plate-vbsample01.catpart":[65540],"pocketing":[16384],"atool.number":[8],"ncborbar":[8],"adl_odt_out":[8],"mfgdrilltool":[8],"mfghorizontallathemachine":[9216],"caamaiinsertppinstruction":[2],"toolpicturename":[8],"width":[8],"deletedirprompt":[8],"before":[18],"cycles":[8],"used":[12801],"deltavalue":[9216],"launched":[111107],"adlodtoutpath":[8],"plane.1":[6144],"nccountecomp.gif":[8],"processlist":[8],"atoolnb":[8],"shows":[111107],"shown":[111107],"manufacturingsetup":[245535],"group":[512],"setup1.getmanufacturingview":[66308],"created":[12],"refactivityname":[18],"-small":[8],"catmain":[134940],"plane.2":[6144],"reponse":[8],"createhtmlfile":[8],"bgcolor":[8],"creates":[241671],"managing":[516],"t-slotting":[16384],"utilisant":[8],"anassembly.name":[8],"mfglathedeltalinedist":[9216],"traitement":[8],"catia.quit":[8],"nltriang":[8],"part":[261644],"values":[4],"insert":[14874],"their":[12288],"point":[81668],"aresource.numberofattributes":[8],"debut":[8],"adlodttmppath":[8],"secondrelimitingelement":[9216],"mfgconicalmilltool":[8],"adds":[65536],"ligne":[8],"move":[18],"process":[261919],"temp":[8],"ncthrmilcomp":[8],"correspondance":[8],"assignment":[74752],"attribut":[9],"thepprdoc":[163840],"atool.tooltype":[8],"getpath":[8],"also":[66049],"anassembly":[8],"activitytype":[9],"gets":[65536],"nctapscomp.gif":[8],"toolnumber":[9],"subdircount":[8],"third":[8192],"myfeature":[768],"uses":[12288],"user":[3098],"plane":[4],"tmlist2.getelement":[6144],"thelogmode":[8],"fin":[8],"maxassemblynb":[8],"catia.documents":[80900],"currentactivity.type":[9],"path":[8],"progactivitylist.getelement":[8],"des":[8],"aprocessname":[8],"trim":[8],"fso.copyfile":[8],"seront":[8],"manufacturing":[94735],"processactivities":[8],"tmlist.getelement":[9216],"vbsystemmodal":[8],"overwrite":[8],"you":[111123],"jump":[65540],"assemblynumber":[9],"mfgexternaltool":[8],"nccounte":[8],"past":[4096],"sel.item":[4],"documentation":[9],"dassault":[111111],"active":[111119],"activityref.issubtypeof":[81686],"corrector":[8],"am":[16384],"manufacturingtoolassembly":[8],"an":[178689],"mfgroundinsert":[8],"deltavalue.value":[9216],"mill":[6144],"canceled":[8],"as":[245535],"at":[28689],"catprocess":[69143],"d'ajouter":[8],"writeprocessstructure":[8],"currentprogram.name":[8],"numberofsetup":[66052],"drive":[12288],"fso.deletefolder":[8],"nccentercomp.gif":[8],"relative":[8],"activitylist.count":[9],"be":[143379],"openlogfile":[8],"bodies":[65540],"facing":[16384],"d1":[9216],"d2":[9216],"mfg_nominal_diam":[8],"d3":[9216],"br":[8],"d4":[9216],"sixth":[8192],"d5":[9216],"designpattern":[65540],"how":[111107],"mfgtaptool":[8],"mytab":[4],"d6":[9216],"d7":[9216],"catdocument":[8],"attrval":[8],"by":[12295],"assembly":[16392],"jumpdistance":[65540],"nldiamnd":[8],"nlexttl":[8],"sel":[4],"anattribut":[8],"parameterisignored":[8],"ce":[8],"topmode":[65540],"set":[245535],"systeme":[8],"plane2":[7168],"mo1.inserttoolmotion":[9216],"initializing":[32768],"plane1":[6144],"procedure":[3096],"writeline":[8],"parrallel":[4096],"sample":[5],"anactivity.issubtypeof":[8],"gestion":[8],"namelength":[8],"nctslott":[8],"currentassembly.getattribute":[9],"setup1.getproductinstance":[66308],"font":[8],"de":[8],"addresourceparameters":[8],"added":[16],"dim":[245535],"language":[134940],"retrieved":[12289],"manufacturingprogramworkbench":[163840],"ncreamer":[8],"hybridbody1":[16128],"du":[8],"subdir":[8],"ignores":[8],"jump.valuatefromstring":[65540],"test.name":[1024],"retrieves":[111111],"startup":[1],"actcur.issubtypeof":[18],"legal":[4],"tm3.getattribute":[6144],"workbench":[245270],"which":[12310],"image":[8],"searches":[32768],"autrement":[8],"test":[9224],"finally":[1],"count":[8192],"aresource.getlistofattributes":[8],"ncthrmil":[8],"et":[8],"ncendmilcomp.gif":[8],"toolcornerradius":[8],"myhole":[768],"partsurface":[65540],"fonction":[8],"parts":[15360],"manpattern.deactivatepoint":[65540],"d'outils":[8],"manufacturingpattern":[65540],"thefiles.item":[8],"lathe":[9224],"setup1.product":[15360],"navlogocat.gif":[8],"part1":[81668],"tooltotallength":[8],"origin":[512],"for":[245535],"mfgcountersinktool":[8],"caamaimachiningpatterncreation.catscript":[65536],"theapplication.startworkbench":[163840],"title":[8],"corrnumber":[8],"retrieving":[32773],"load":[134160],"related":[4],"mfgdoc1.selection":[4],"axissystem":[768],"compensationimagefromtool":[8],"tm2.getattribute":[6144],"mfgtrigoninsert":[8],"relimitingelements":[2048],"false":[8],"go":[79366],"length":[8],"machaxis":[768],"tm6.getattribute":[9216],"gt":[8],"une":[8],"hole":[768],"existing":[163848],"nbignoredparameters":[8],"catiabase":[3840],"print":[8],"mfgfeatures":[768],"atool":[8],"setup":[245263],"manufacturingtoolcorrector":[8],"assign":[78340],"select":[12],"program.1":[16384],"hr":[8],"activitylist":[9],"output":[1],"axissystems.item":[768],"mo.inserttoolmotion":[6144],"else":[8],"selectedelement.value":[4],"text":[1],"if":[245535],"partdocument1":[80900],"catscript":[4096],"surface":[65540],"in":[111115],"theproduct":[163840],"index":[8],"is":[111131],"l'affichage":[8],"it":[111115],"loading":[32768],"astream":[8],"fiche":[8],"ppinstr":[18],"adl_odt_slash":[8],"opens":[2],"correcteurs":[8],"hole.4":[65540],"hole.2":[65540],"fso":[8],"hole.3":[65540],"pprint":[18],"hole.1":[65540],"program1.moveoperation":[18],"returnedval":[8],"anassembly.assemblytype":[8],"toolname":[9],"errval":[8],"mill_d_10":[16384],"l'ecriture":[8],"bodies1":[65540],"myfeature.origingroup":[768],"adl_odt_tmp":[8],"file":[111115],"inserted":[2],"stream":[1],"cellpadding":[8],"mfgptdeltadistance":[6144],"emptyfolder":[8],"catiacomponentpath":[8],"table":[8],"myfeature.setpartaxissystem":[768],"checkmode":[6144],"could":[8192],"change":[16393],"mo.settool":[6144],"l'entete":[8],"tmlist.count":[9216],"la":[8],"instruction":[18],"machine":[9216],"motions":[15360],"currentprogram":[9],"le":[8],"thesetup.product":[163840],"li":[8],"autre":[8],"machaxis.setfeature":[768],"manpattern.reverse":[65540],"use":[111111],"fso.createfolder":[8],"lt":[8],"mfgptdeltamode":[6144],"caamaimanagemachiningaxissystem.catscript":[512],"main":[3848],"integer":[3080],"ncdrills":[8],"createoneassemblysheet":[8],"while":[8],"corrlengthnumber":[8],"second":[12288],"thefiles.count":[8],"catia.documents.item":[768],"getelement":[12288],"that":[11280],"manufacturingtoolmotion":[15360],"setup1.programs":[16146],"part1.axissystems":[768],"ffffff":[8],"tabatt":[8],"actinprog.count":[18],"asstool":[8],"d'erreur":[8],"mm":[65536],"mo":[6144],"astring":[8],"fso.fileexists":[8],"-1":[8],"liste":[8],"vbscript":[134940],"theprocess.childrenactivities":[163840],"dependante":[8],"includes":[111107],"tabtoolname":[8],"preserve":[8],"createdfolder":[8],"my":[18],"atextstream":[9],"steps":[111107],"ncreamercomp.gif":[8],"thelogfile.openastextstream":[8],"nlgrvfrl":[8],"entry":[3840],"isatest":[8],"nc":[32768],"ne":[8],"true":[13],"retrieve":[212767],"mfgseqmotionpoint":[6144],"position":[14354],"adlodtout":[8],"systèmes":[111107],"manufacturingmachine":[9216],"no":[24],"box":[18],"writetool":[8],"delete":[8],"nombre":[8],"activates":[65536],"defaultdoctarget":[8],"inputbox":[26],"sous":[8],"manpattern.getnumbers":[65540],"of":[114205],"tabtool":[8],"ncmddrls":[8],"ok":[8],"make":[32768],"mfgseqmotionlathefollow":[9216],"manpattern.getanattribute":[65540],"on":[79884],"macro":[245279],"fichier":[8],"mfgptdeltaparallelline":[6144],"or":[8201],"atextstream.close":[8],"gostd":[9216],"valeur":[8],"src":[8],"ou":[8],"kbb":[8],"ncmillingtoolassembly":[8],"nctslottcomp.gif":[8],"mfglathetoolassembly":[8],"mfglathesequentialoperation":[9216],"offsetvalue":[6144],"manufacturingoperation":[16128],"childs.item":[245535],"cellspacing":[8],"currentsetup.issubtypeof":[9],"pp":[9234],"ps":[4],"anactivity.name":[8],"part1.bodies":[65540],"mo1.getlistoftoolmotions":[9216],"delta":[15360],"pourrait":[8],"caamaiinsertlathetoolmotion":[8192],"coordinatesystem":[768],"maxtoolnb":[8],"child.issubtypeof":[245526],"sample.catpart":[32768],"programlist.count":[777],"dependant":[8],"childs.count":[245534],"tm2.setgeometry":[15360],"assemblies":[1],"std":[8192],"module":[111107],"them":[65536],"sel.selectelement2":[4],"then":[245535],"execute":[134160],"removepartsurfaces":[65536],"mfgtwosideschamferingtool":[8],"rc":[4],"d'un":[8],"filename":[8],"mfgthreadmilltool":[8],"programs":[9],"starting":[32768],"t1":[9216],"t3":[6144],"count1":[768],"sub":[245534],"activity":[114207],"assemblyname":[9],"scan":[9],"association":[32768],"mid":[8],"global":[3072],"mfgseqmotionlathegostd":[9216],"toolcuttinglength":[8],"long":[8],"partlathe_toolmotion.catpart":[9216],"myfeature.originnumber":[768],"into":[4],"nbatt":[8],"current":[245535],"mo.getlistoftoolmotions":[6144],"si":[8],"catia.systemservice.environ":[8],"usedtool.number":[8],"lecture":[8],"so":[8192],"destruction":[8],"holes":[65540],"prismatic":[242182],"tabtoolstatus":[8],"variables":[68616],"thehtmlfile.openastextstream":[9],"adl_odt_in":[8],"associates":[163840],"nbmo":[15360],"tm5.setgeometry":[9216],"one":[12289],"tm7.setgeometry":[9216],"asstoolname":[8],"currentassembly":[9],"drilling":[16384],"launch":[32768],"store":[8192],"td":[8],"face":[4],"diameterattribut":[8],"currentactivity.toolassembly":[9],"writecaption":[8],"tm8.setgeometry":[9216],"gettoolassemblyimage":[8],"activityref":[81686],"associated":[163840],"caamaitoollistdocumentation.catscript":[1],"open_body.1":[16128],"program1":[16146],"geometry":[15360],"fourth":[8192],"to":[245535],"features.add":[65540],"operation":[31752],"open":[245279],"tr":[8],"replaying":[111107],"err.number":[8],"mfgendmilltool":[8],"folders":[8],"numbers":[65540],"atelier":[8],"inside":[12288],"horizontal":[9216],"associating":[32768],"diameter":[8],"variant":[81676],"un":[8],"catia.documents.add":[163840],"up":[131088],"written":[1],"five":[32769],"generate":[1],"nlinttl":[8],"mfg_apt_diameter":[8],"outil":[8],"coordinate":[512],"this":[111111],"mfgview.manufacturingfeatures":[65540],"juillet2000":[8],"vb":[3093],"currentassembly.insert":[8],"look":[1],"modification":[6144],"caamaitoollistdocumentation":[1],"tmlist":[9216],"geometric":[4096],"toollength":[8],"allow":[3090],"reasons":[65536],"qui":[8],"toolchange":[9],"mfgto":[2048],"needed":[1],"sequential":[15360],"changes":[1],"destination":[8],"number3":[65536],"caamaiinitializesetup.catscript":[32768],"mo1":[9216],"we":[12288],"afolder.subfolders":[8],"defaulthtmlappliname":[8],"ncborbarcomp.gif":[8],"nlsquare":[8],"shapes":[4],"ignoredparameters":[8],"definition":[8],"manufacturingtool":[8],"performances":[65536],"anassembly.getattribute":[8],"thepartdoc.product":[163840],"pointtopoint":[6144],"reading":[6149],"line.1":[6144],"mfgdoc1.getitem":[81695],"compensation":[8],"location":[18],"step":[8200],"ncspodri":[8],"line.2":[6144],"line.3":[6144],"trouve":[8],"caascdmaiusecases":[111107],"program1.childrenactivities":[18],"mfgthreadinternaltool":[8],"t1_end":[16384],"user-defined":[18],"type":[28681],"numberofactivity":[9],"aparam":[8],"scans":[32768],"acorr.lengthnumber":[8],"href":[8],"nom_du_parametre":[8],"presence":[8],"between":[40960],"body1.shapes":[65540],"folderpath":[8],"hybridshapepointcoord2":[768],"method":[12288],"nctschmfcomp.gif":[8],"dans":[8],"mfgthreadexternaltool":[8],"issmall":[8],"anobj.getattributenlsname":[8],"aprocess":[9],"axial":[6144],"forwriting":[9],"acceptcomment":[8],"lors":[8],"part1.hybridbodies":[16128],"shapes1.item":[65540],"mfgseqmotiondelta":[6144],"mfg_cone_diameter_2":[8],"activityname":[9],"document1.close":[8],"mfg_cone_diameter_1":[8],"mfgdoc1.name":[8],"word":[9234],"rootactivityname":[8],"toolbodydiameter":[8],"anactivity.programs":[8],"flag":[8],"mfgmultidiamdrilltool":[8],"mechanicaltool.1":[65540],"myfeature.setoriginpoint":[768],"point.3":[6144],"hybridshapes1.item":[16128],"point.2":[6144],"theapplication":[163840],"point.1":[6912],"hybridbodies1":[16128],"tools":[9],"specified":[18],"feature":[66304],"body1":[65540],"get":[210944],"setup1":[81686],"tmlist2.count":[6144],"mfgseqmotionposition":[6144],"removedirectory":[8],"ncfacmilcomp.gif":[8],"chemin":[8],"thelogname":[8],"existe":[8],"mfgseqmotionlatheindirv":[9216],"anobj.getattribute":[8],"thepartdoc":[163840],"err.clear":[8],"insertcomment":[8],"elements":[8192],"located":[111107],"usedinsert.inserttype":[8],"thehtmlfile":[9],"comme":[8],"first":[12288],"argument":[12288],"corr":[8],"data":[1],"t3_t-slotter_d_50":[16384],"anassembly.comment":[8],"axis":[512],"currentprogram.activities":[9],"reference":[4098],"filepath":[8],"gettoolimage":[8],"t2_drill_d_10":[16384],"afolder":[8],"caamaiinsertaxialtoolmotion":[4096],"only":[73728],"should":[2],"create":[210455],"gettoolstdimage":[8],"from":[78337],"html":[9],"guidingelements":[6144],"inserting":[12290],"nclathetoolassembly":[8],"doivent":[8],"offset":[4096],"resource":[8],"hybridbodies1.item":[16128],"anassembly.insert":[8],"partdoc1.part":[768],"files":[8],"continueifexistingfolder":[8],"mfgtriangularinsert":[8],"here":[8],"img":[8],"ncspodricomp.gif":[8],"acorr.number":[8],"gif":[8],"actinprog.item":[18],"line":[12288],"writeassemblytable":[8],"deltamode.valuatefromstring":[9216],"error":[8],"can":[1],"myfeature.setoriginzdirection":[768],"operations":[8],"array":[65536],"parameter":[71693],"value":[12288],"diameterattribut.value":[8],"quantity":[245535],"motion":[15360],"mfgfacemilltool":[8],"will":[143378],"aname":[8],"tm4.getattribute":[9216],"mfgboringandchamferingtool":[8],"reads":[4096],"resources":[4],"valuating":[4096],"ncendmil":[8],"follow":[9216],"instead":[4096],"part_toolmotion.catpart":[6144],"tableau":[8],"boolean":[8],"corresponding":[514],"numberofprogram":[777],"asubdir":[8],"bodies1.item":[65540],"variable":[111115],"slash":[8],"mo1.settool":[9216],"selectedelement":[4]}}}