{"CAAPdiTechArticles": {"FileList":["CAAPdiRADEInstallation.htm","CAAPdiENOVIALCAAPIInstallation.htm","CAAPdiCATIAAPIInstallation.htm","CAAPdiWindowsRADEBatchInstallation.htm","CAAPdiDELMIAAPIInstallation.htm","CAAPdiSoftwareManagement.htm","CAAPdiRADEPreInstallation.htm","CAAPdiUnixBatchInstallation.htm","CAAPdiWindowsBatchInstallation.htm","CAAPdiUnixRADEBatchInstallation.htm","CAAPdiVbtLicensing.htm"],"TitleList":["Installing CAA RADE V5 Products","Installing CAA ENOVIA V5 API Products","Installing CAA CATIA V5 API Products","Installing CAA RADE V5 Products in Batch Mode with Windows","Installing CAA DELMIA V5 API Products","Managing Your Installed CAA V5 APIs","Preparing for CAA RADE V5 Products Installation","Installing CAA V5 API Products in Batch Mode with UNIX","Installing CAA V5 API Products in Batch Mode with Windows","Installing CAA RADE V5 Products in Batch Mode with UNIX","Setting up the Licensing for CAA RADE V5 Products"],"WordList":{"flavors":[1024],"illustrating":[22],"german":[520],"prepare":[64],"language-indexed":[521],"me2.slt.caa2":[384],"-caac":[32],"quickest":[32],"your":[1791],"remote":[1056],"without":[927],"setting":[1025],"via":[1024],"these":[2024],"-caar":[32],"would":[1],"double-click":[23],"visual":[1089],"-caai":[32],"near":[1024],"navigate":[1],"cdc":[1545],"dealing":[64],"instruct":[1024],"cdg":[1024],"require":[64],"click":[1143],"version":[2025],"add-ons":[1024],"contains":[904],"folder":[287],"reserved":[2047],"nochecktckport":[520],"v5-6b2021_xxxx_rade":[1],"appropriate":[265],"providing":[1],"radecatsettingpath":[1024],"least":[128],"roll":[32],"example":[1663],"result":[22],"characters":[9],"rolling":[32],"same":[1951],"procedures":[23],"cdc.slt":[520],"after":[1057],"behavior":[1],"close":[1],"resolved":[32],"a":[2047],"committed":[32],"c":[1353],"e":[8],"learn":[1024],"the":[2047],"licenser":[1025],"licenses":[1025],"s":[1025],"u":[512],"x":[1],"days":[1024],"information":[1079],"correct":[1024],"official":[1],"suffixed":[32],"empty":[1],"red":[1024],"wish":[1153],"belonging":[65],"leave":[22],"cross-referenced":[1025],"exceed":[9],"copying":[23],"finish":[87],"licensedir":[520],"uncheck":[65],"add":[553],"area":[23],"need":[1121],"elr":[16],"check":[1599],"list":[1983],"article":[1024],"users":[1064],"port":[520],"pd1":[4],"useful":[520],"cid":[1],"reg_dword":[32],"technical":[1024],"production":[1],"divided":[1024],"provided":[1047],"choose":[1079],"interface":[905],"directory":[959],"remove":[585],"prevent":[23],"expanded":[1024],"nodelock":[1545],"provides":[1024],"responsible":[1024],"root":[32],"end":[1056],"menus":[64],"lines":[1],"caa2":[384],"redirector":[32],"identify":[33],"-list":[904],"perform":[904],"message":[1056],"pdc":[2],"special":[2047],"modify":[1057],"with":[2047],"caa_rade.v5r31.b31":[1],"environment":[1545],"pdg":[4],"vpm":[2],"service":[33],"there":[33],"detected":[32],"syntax":[904],"well":[1024],"suitable":[1],"splash":[1],"copyright":[2047],"named":[1024],"configurations":[1983],"release":[65],"delivered":[640],"entire":[1],"excepted":[520],"number":[1047],"period":[1024],"nothing":[1],"specify":[1047],"understand":[1024],"confirmation":[1],"intel":[264],"exit":[1111],"system":[1641],"install":[1023],"animated":[23],"catsoftwaremgtb.exe":[32],"32-bit":[8],"other":[21],"save":[33],"mandatory":[1],"local":[1056],"screenshots":[22],"valid":[1024],"aix":[545],"top":[1120],"acquiring":[1024],"indicates":[1024],"rights":[2047],"have":[2047],"share":[1],"product":[1983],"reminder":[640],"picture":[1],"2126..r1":[1024],"names":[927],"removed":[64],"disable":[1088],"future":[1],"stored":[1024],"x86":[64],"deactivating":[32],"catstart":[1057],"copied":[23],"screen":[23],"-caai3":[32],"lets":[1951],"identical":[1025],"mode":[1960],"saturation":[32],"pages":[32],"etc":[1024],"whether":[1047],"net":[1024],"all":[2047],"always":[97],"new":[1129],"settings":[1055],"read":[32],"already":[1121],"below":[1248],"applicable":[64],"less":[1024],"prod.prd.caa2":[384],"prompted":[55],"tool":[1057],"2118..r1":[1024],"-caai1":[32],"apis":[439],"simplified":[520],"-caai2":[32],"were":[22],"basic":[1024],"unix":[1719],"v5r28":[64],"v5r29":[64],"locate":[64],"-tckservername":[520],"cause":[32],"v5r20":[64],"v5r21":[64],"lca":[2],"v5r22":[64],"v5r24":[64],"v5r25":[64],"running":[2047],"parameterized":[1024],"and":[2047],"chose":[22],"define":[1024],"working":[1024],"0-9":[8],"declared":[1024],"buttons":[1025],"warnings":[1024],"-tckboot":[520],"v5r30":[64],"v5r31":[520],"italian":[520],"korean":[520],"specific":[1024],"any":[1079],"followed":[54],"csc":[1024],"encyclopedia":[1023],"application":[1032],"simplified_chinese":[520],"consists":[1024],"until":[1024],"maintain":[64],"a-z":[8],"decided":[32],"caacenv5default.htm":[22],"integrity":[32],"java":[1024],"english":[520],"exclusive":[904],"let":[1],"api":[406],"press":[1024],"welcome":[23],"envdir":[1],"displayed":[1047],"cache":[32],"using":[2047],"imminent":[1024],"containing":[1832],"want":[1463],"completed":[23],"deteriorate":[32],"mount":[640],"pack":[33],"each":[1111],"-nochecktckport":[520],"offering":[1024],"must":[2047],"enroll":[520],"delmia":[2047],"cut":[1024],"scanning":[23],"another":[137],"automatically":[32],"document":[1056],"jdv.slt":[520],"recommend":[23],"acquire":[1024],"two":[1025],"default":[1929],"uninstall":[97],"are":[2047],"does":[1545],"taken":[22],"where":[1983],"caainstalldir":[128],"takes":[1],"latest":[64],"modifying":[32],"languages":[521],"services":[32],"describes":[1024],"notices":[2047],"sich.font":[520],"such":[1495],"summarizes":[64],"jdv":[520],"supported":[65],"privileges":[87],"documents":[8],"remains":[1],"run":[2017],"microsoft":[1],"startb":[8],"b31_rade":[1],"unable":[32],"either":[55],"has":[575],"starts":[23],"acquired":[1024],"those":[23],"-option":[32],"given":[520],"last":[1],"let's":[32],"batch":[1960],"develop":[64],"utilizentcaching":[32],"aug":[32],"longer":[1024],"checks":[32],"kin.prd.caa2":[384],"-direnv":[1],"name":[1961],"spaces":[926],"overall":[32],"kohg.font":[520],"page":[54],"assume":[32],"rtinstalldir":[384],"parameters":[32],"updated":[23],"catvbtserver":[64],"next":[1047],"rade_installation_path":[1025],"color":[1024],"string":[9],"vs2008":[64],"rade":[1641],"vs2005":[64],"catia":[2047],"button":[1031],"not":[1663],"central":[23],"systemes":[329],"dmc.prd":[520],"now":[64],"customizing":[1],"hours":[1024],"green":[1024],"yes":[23],"start":[2047],"reserving":[1024],"windows":[1407],"editing":[32],"manage":[1056],"target":[1088],"what":[1111],"catvbtlicenser.exe":[1025],"refer":[65],"short":[1056],"time":[1463],"window":[1310],"applications":[1088],"studio":[65],"right-hand":[1025],"interactive":[1025],"program":[351],"three":[1120],"when":[1577],"required":[87],"excluded":[520],"list_to_unload":[904],"options":[32],"unload":[904],"enter":[1983],"issued":[1024],"case":[1025],"dashboard":[1025],"b31rade":[1],"identifier":[41],"identifies":[8],"images":[23],"catsoftwaremgt.exe":[32],"double":[64],"dates":[1024],"priority":[1],"provide":[22],"rely":[23],"quot":[1544],"browse":[1],"explicitly":[1024],"log":[119],"exercise":[32],"enabled":[1024],"computer":[1143],"-unregserver":[1],"irad6":[1024],"clicking":[1047],"licensing":[1025],"enables":[1024],"means":[1024],"prod":[384],"more":[1665],"display":[1047],"kill":[32],"servername":[520],"left-hand":[1025],"choice":[543],"hanging":[23],"levels":[96],"indicator":[23],"shut":[23],"mkmancpp":[1024],"compact":[1024],"before":[1079],"tell":[1024],"used":[128],"compilers":[64],"mkmk":[1088],"looks":[22],"his":[1024],"shows":[1089],"shown":[1046],"individualize":[1024],"checked":[1078],"pointing":[1024],"v5-6b2017":[1024],"consider":[1024],"described":[33],"group":[87],"obtain":[904],"otherwise":[87],"corrupted":[32],"package":[64],"visible":[9],"created":[1577],"minutes":[119],"particular":[1024],"history":[1056],"both":[65],"important":[1],"v5-6b2021":[22],"keep":[32],"creates":[648],"managing":[32],"option":[1598],"code-generator":[64],"part":[1441],"values":[520],"insert":[23],"their":[1],"point":[1697],"-tckserverport":[520],"me2.slt":[384],"win_b64":[41],"administrator":[1111],"fonts":[521],"radelicensing.xml":[1024],"amount":[23],"move":[23],"process":[1],"restore":[32],"also":[1079],"enough":[1],"clean":[64],"setup.exe":[1],"recommended":[33],"successively":[64],"listed":[23],"build":[65],"various":[1024],"user":[1961],"been":[1079],"ident":[1],"mutually":[904],"tooltip":[1024],"conversely":[32],"der":[2],"path":[904],"depending":[23],"doesn't":[648],"reflects":[23],"you":[2047],"addition":[520],"sure":[904],"going":[1024],"documentation":[64],"dassault":[2047],"active":[1024],"-desktop":[1],"an":[95],"whose":[32],"as":[1527],"at":[1705],"assigned":[87],"drive":[287],"relative":[1024],"deal":[64],"be":[1791],"consequently":[1024],"choosing":[32],"customize":[1024],"virus":[23],"how":[1111],"see":[65],"systems":[23],"by":[2047],"kanj.font":[520],"panel":[1025],"enrolled":[1],"compared":[8],"cd":[1024],"enabling":[23],"mind":[32],"contain":[1],"set":[1047],"ch":[520],"committing":[32],"column":[64],"entered":[1056],"familiar":[23],"involve":[1],"possible":[1],"procedure":[23],"grayed":[1024],"underscore":[9],"maximum":[1024],"digits":[8],"validity":[1056],"jul":[1024],"added":[32],"language":[521],"do":[1121],"dir":[904],"-delcatenv":[1],"down":[23],"launching":[1024],"chinese":[520],"correctly":[1],"japanese":[520],"later":[521],"startup":[64],"useless":[520],"warning":[1024],"exclude":[520],"preceded":[1033],"5-6":[1],"possibly":[32],"needs":[1024],"which":[2047],"dedicated":[1],"image":[1024],"eg":[1024],"test":[1],"-nofonts":[520],"de-installation":[23],"-newdir":[648],"take":[119],"parts":[1024],"aix_a":[1057],"expiration":[1024],"carry":[64],"however":[33],"dassaultsystemes":[648],"some":[1056],"code-designer":[64],"blank":[904],"blanks":[9],"requesting":[1024],"additional":[521],"for":[2047],"back":[32],"fr":[520],"v5-6r2012":[64],"duration":[1024],"getting":[32],"mkodt":[1024],"noserver":[520],"alert":[1024],"confirms":[33],"client":[552],"ga":[32],"just":[1024],"ge":[520],"caadoc":[22],"cd-rom":[927],"custom":[23],"go":[286],"stroke":[520],"home":[22],"existing":[1544],"approximately":[87],"management":[1057],"setup":[23],"dmc":[1544],"v5-6r2020_install2":[32],"articles":[1],"he":[1024],"prompt":[287],"showing":[23],"subset":[22],"overwrites":[32],"very":[1],"select":[287],"advanced":[1056],"bin":[1057],"helping":[54],"lanmanworkstation":[32],"bit":[545],"attempt":[1],"soon":[1024],"authorization":[32],"four":[1],"nodelocked":[1025],"id":[1024],"if":[2047],"1999-2019":[1088],"french":[520],"v5-6r2021":[22],"v5-6r2020":[32],"in":[2047],"made":[520],"is":[1983],"being":[64],"it":[1705],"hkey_local_machine":[32],"-code":[384],"traditional":[520],"uninstalladdinvs2005.reg":[64],"1999-2020":[959],"asks":[1],"served":[1024],"explorer":[64],"warned":[1024],"doc":[22],"opens":[64],"become":[1],"status":[1024],"rade31":[1],"server":[1545],"customized":[64],"progressively":[23],"jp":[520],"installations":[65],"caaradeinstalldir":[520],"skip":[1],"sub-list":[1024],"mac":[16],"mab":[1024],"products":[2047],"file":[1641],"caav5homepage.htm":[22],"table":[64],"ko":[552],"may":[1121],"within":[1024],"could":[1],"change":[1664],"kr":[520],"defining":[1024],"menu":[1097],"verbose":[904],"places":[1],"serverport":[520],"able":[1111],"trch.font":[520],"complete":[23],"startcaab":[256],"use":[1631],"enrolls":[520],"several":[1057],"suffix":[384],"second":[23],"that":[1727],"usr":[640],"sufficient":[1024],"than":[2015],"communication":[520],"different":[1111],"logs":[1024],"administrators":[87],"selected":[23],"level":[104],"occur":[32],"follows":[32],"definitive":[521],"steps":[23],"plus":[1024],"becomes":[1],"chosen":[1025],"license":[1545],"disk":[55],"entries":[9],"task":[87],"-env":[1],"savers":[23],"background":[23],"lists":[1983],"add-on":[1024],"errors":[32],"systèmes":[2047],"since":[64],"no":[1641],"belong":[1111],"code":[1079],"p3":[4],"envname":[1],"certificate":[520],"appears":[1079],"box":[119],"installing":[1023],"symbols":[520],"switch":[1024],"dialog":[119],"-a":[1],"-d":[521],"imported":[1024],"of":[2047],"-e":[1],"reserve":[1025],"-h":[904],"ok":[97],"make":[927],"informs":[1047],"-l":[936],"on":[2047],"allows":[1056],"execution":[1024],"processes":[32],"or":[2047],"os":[1577],"-s":[640],"-u":[648],"unregister":[64],"-v":[904],"control":[1065],"orange":[1024],"due":[55],"online":[22],"inform":[1024],"startcaa.exe":[22],"upper":[1024],"about":[1057],"commit":[32],"registered":[1],"granted":[1024],"meaning":[32],"above":[1545],"concurrently":[23],"expiry":[1024],"prompts":[22],"they":[97],"boxes":[1],"b22":[64],"ole":[1],"them":[23],"then":[1343],"remaining":[1024],"something":[22],"concepts":[23],"highest":[64],"expire":[1024],"xxxx":[1],"programs":[1343],"rm":[1],"starting":[22],"aix_a64":[545],"unloads":[904],"-all":[904],"b31":[905],"checking":[1056],"components":[1],"nevertheless":[64],"access":[584],"customization":[65],"advisable":[1],"global":[1],"extended":[1],"remember":[1024],"into":[1047],"offline":[1024],"current":[87],"boots":[520],"operating":[1631],"free":[520],"so":[1],"caution":[32],"key":[1056],"rollback":[32],"computer's":[32],"silent":[640],"manager":[1089],"necessary":[86],"though":[1],"64-bit":[8],"one":[1790],"launch":[1047],"started":[640],"releases":[1],"single":[1111],"appear":[1056],"associated":[520],"progress":[23],"troubleshooting":[32],"to":[2047],"open":[1384],"v5":[2047],"but":[1088],"v6":[64],"symbol":[520],"workspace":[1024],"separate":[927],"available":[1663],"numbers":[1025],"rules":[32],"enclosed":[904],"language-specific":[1],"loaded":[64],"envovia":[64],"whenever":[1024],"up":[1089],"written":[1024],"commands":[65],"extreme":[32],"solutions":[32],"this":[2047],"please":[32],"look":[904],"once":[55],"catsoftwaremgt":[32],"know":[1],"de-install":[1],"vs":[64],"allow":[1078],"installed":[2047],"needed":[87],"changes":[22],"destination":[23],"proper":[32],"rule":[64],"assistance":[23],"we":[23],"expired":[1024],"missing":[32],"throughout":[1],"definition":[2],"unregistered":[64],"tckuninstall":[1],"license.lic":[520],"registry":[41],"add-in":[64],"previous":[119],"apply":[1025],"reading":[32],"popup":[1024],"reinstall":[32],"location":[1057],"step":[23],"software":[695],"reach":[1],"graphical":[904],"kin.prd":[384],"conf":[384],"during":[1056],"foreground":[1],"none":[1024],"displays":[1928],"type":[1983],"preparation":[64],"problem":[32],"enable":[1025],"between":[1024],"-rf":[1],"still":[64],"-ident":[8],"work":[1088],"-run":[1057],"come":[1024],"catenv":[521],"installroot":[32],"packs":[32],"installs":[1],"-lic":[520],"exist":[1673],"catsoftwaremgtb":[32],"examples":[904],"among":[22],"anyone":[23],"following":[2047],"specifies":[1951],"our":[23],"tools":[1663],"specified":[520],"out":[1089],"get":[32],"installation":[1023],"conf.slt.caa2":[384],"copy":[640],"-tckmode":[520],"explains":[23],"informed":[1024],"currentcontrolset":[32],"restart":[1544],"abstract":[1056],"help":[904],"cannot":[1577],"first":[1567],"date":[1024],"uppercase":[9],"argument":[904],"data":[40],"mkscc":[1024],"existence":[32],"dashboards":[1024],"intel_a":[1096],"space":[55],"catvbtlicenser":[1025],"tab":[32],"only":[1641],"should":[1111],"consequences":[32],"create":[1],"from":[1143],"tag":[1024],"development":[1025],"like":[1950],"sequence":[23],"preparing":[65],"proposed":[1],"cleaned":[1],"files":[895],"add-ins":[65],"here":[22],"note":[1759],"caa":[2047],"msgcatalog":[520],"configuration":[1951],"line":[33],"interact":[1],"error":[32],"windows-compliant":[23],"network":[1056],"can":[2047],"operations":[1024],"servers":[1024],"tck":[521],"value":[1056],"-nolang":[520],"carried":[1],"will":[1783],"match":[64],"groups":[1024],"resources":[584],"allowing":[1024],"command":[2025],"enovia":[2047],"performance":[32],"corresponding":[1024],"serial":[1024],"variable":[1024],"arguments":[904],"locations":[23],"intend":[32]}}}